gradio_dp_machine/__init__.py
gradio_dp_machine/dp_machine.py
gradio_dp_machine/dp_machine.pyi
gradio_dp_machine/templates/component/index.js
gradio_dp_machine/templates/component/style.css
gradio_dp_machine/templates/example/index.js
gradio_dp_machine/templates/example/style.css
gradio_dp_machine-0.0.3.dist-info/METADATA
gradio_dp_machine-0.0.3.dist-info/WHEEL
gradio_dp_machine-0.0.3.dist-info/RECORD
